{
  "AA_CCA": {
	"CCa Main|0": [0.902, 0.745, 0.239, 1],
	"CCa Main|1": [0.851, 0.533, 0.255, 1],
	"CCa Main|2": [0.647, 0.125, 0.098, 1],
	"CCa Main|3": [0, 0, 0, 1],
	"CCa Mech Head|0": [0.189, 0.162, 0.153, 1],
	"CCa Mech Head|1": [0.779, 0.175, 0.348, 1],
	"CCa Mech Head|2": [0.857, 0.791, 0.703, 1],
	"CCa Mech Head|3": [0, 0, 0, 1],
	"2nd Cupcake|0": [0.824, 0.306, 0.427, 1],
	"2nd Cupcake|1": [0.443, 0.298, 0.216, 1],
	"2nd Cupcake|2": [0.227, 0.098, 0.067, 1],
	"2nd Cupcake|3": [1, 0.569, 0, 1],
	},
	"AA_FD": {
	"FD Main|0": [0.58, 0.333, 0.129, 1],
	"FD Main|1": [0.824, 0.502, 0.161, 1],
	"FD Main|2": [0.129, 0.129, 0.129, 1],
	"FD Main|3": [0.345, 0.188, 0.125, 1],
	"FD Clothes|0": [0.861, 0.208, 0, 1],
	"FD Clothes|1": [1, 0.408, 0.357, 1],
	"FD Clothes|2": [1, 1, 1, 1],
	"FD Clothes|3": [0, 0, 0, 1],
	"FD Mech Head|0": [0.189, 0.162, 0.153, 1],
	"FD Mech Head|1": [0.7, 0.014, 0.014, 1],
	"FD Mech Head|2": [0.857, 0.791, 0.703, 1],
	"FD Mech Head|3": [1, 1, 1, 1],
	},
	"PROP_MRHUGS_2": {
	"Mr Hugs 2|0": [0.9, 0.39, 0.135, 1],
	"Mr Hugs 2|1": [0.46, 0.332, 0.235, 1],
	"Mr Hugs 2|2": [0.53, 0.155, 0.079, 1],
	"Mr Hugs 2|3": [0.79, 0.768, 0.671, 1],
	},
}
